[
    
    [
    {
    "Player":"Julian Scanlon",
    "Stat":"GWG",
    "Image":"image8"
    },
    {
    "Player":"Easton Goofellow",
    "Stat":"19-26 Saves .826 SV%",
    "Image":"image13"
    },
    {
    "Player":"Mason Perry",
    "Stat":"3 Assists",
    "Image":"image9"
    }],
    
    [
        {
        "Player":"test",
        "Stat":"GWG",
        "Image":"image1"
        },
        {
        "Player":"Eaw",
        "Stat":"19-26 Saves .826 SV%",
        "Image":"image12"
        },
        {
        "Player":"rry",
        "Stat":"3 Assists",
        "Image":"image3"
        }]
]

    
